cygrpc/__init__.py
cygrpc/__main__.py
cygrpc/cli.py
cygrpc/server.py
cygrpc/gateway/__init__.py
cygrpc/gateway/errors.py
cygrpc/gateway/http.py
cygrpc/gateway/rest_gateway.py
cygrpc/gateway/middleware/__init__.py
cygrpc/gateway/middleware/base.py
cygrpc/gateway/middleware/log_middleware.py
cygrpc/gateway/middleware/mongo_errors_middleware.py
cygrpc/gateway/middleware/pre_middlewares.py
cygrpc/gateway/plugins/__init__.py
cygrpc/gateway/proxy/__init__.py
cygrpc/gateway/proxy/middleware.py
cygrpc/gateway/proxy/reverse_stub.py
cygrpc/gateway/proxy/router.py
cygrpc/interceptors/__init__.py
cygrpc/interceptors/cygrpcInterceptor.py
cygrpc/interceptors/auth/__init__.py
cygrpc/interceptors/auth/cygrpcAuthInterceptor.py
cygrpc/protobuf_to_dict/__init__.py
cygrpc/protobuf_to_dict/convertor.py
cygrpc/utils/__init__.py
cygrpc/utils/extractor.py
cygrpc-1.0.4.post6.dist-info/METADATA
cygrpc-1.0.4.post6.dist-info/WHEEL
cygrpc-1.0.4.post6.dist-info/entry_points.txt
cygrpc-1.0.4.post6.dist-info/top_level.txt
cygrpc-1.0.4.post6.dist-info/RECORD
