Metadata-Version: 2.1
Name: cygrpc
Version: 1.0.4.post6
Summary: gRPC Micro framework
Home-page: https://github.com/cuemby/python-cygrpc
Author: Fabio Moreno
Author-email: fabio.moreno@cuemby.com
License: MIT
Platform: UNKNOWN
Classifier: License :: OSI Approved :: MIT License
Classifier: Programming Language :: Python :: 3
Classifier: Programming Language :: Python :: 3.6
Classifier: Programming Language :: Python :: 3.7
Classifier: Programming Language :: Python :: 3.8
Requires-Python: >=3.6
Requires-Dist: Paste
Requires-Dist: bottle
Requires-Dist: bottle-cors
Requires-Dist: grpcio-tools (==1.23.0)
Requires-Dist: grpcio (==1.23.0)
Requires-Dist: twine
Requires-Dist: wheel
